<?xml version="1.0" encoding="utf-8"?>
<savedqueries xmlns:xsi="http://www.w3.org/2001/XMLSchema-instance">
  <savedquery>
    <IsCustomizable>1</IsCustomizable>
    <CanBeDeleted>0</CanBeDeleted>
    <isquickfindquery>0</isquickfindquery>
    <isprivate>0</isprivate>
    <isdefault>1</isdefault>
    <savedqueryid>{0bb85e6c-5543-414b-bb3b-0f085c788477}</savedqueryid>
    <layoutxml>
      <grid name="resultset" jump="tra_name" select="1" icon="1" preview="1">
        <row name="result" id="tra_monthlybusinessexpensesid">
          <cell name="tra_name" width="300" />
          <cell name="tra_monthlyactual" width="130" />
        </row>
      </grid>
    </layoutxml>
    <querytype>0</querytype>
    <fetchxml>
      <fetch version="1.0" mapping="logical">
        <entity name="tra_monthlybusinessexpenses">
          <attribute name="tra_monthlybusinessexpensesid" />
          <attribute name="tra_name" />
          <order attribute="tra_name" descending="false" />
          <filter type="and">
            <condition attribute="statecode" operator="eq" value="0" />
          </filter>
          <attribute name="tra_monthlyactual" />
        </entity>
      </fetch>
    </fetchxml>
    <IntroducedVersion>1.0</IntroducedVersion>
    <LocalizedNames>
      <LocalizedName description="Active Monthly Business Expenses" languagecode="1033" />
    </LocalizedNames>
  </savedquery>
</savedqueries>